segmentpy/SegmentPy.py
segmentpy/__init__.py
segmentpy/_taskManager/ActViewer_design.py
segmentpy/_taskManager/ActViewer_logic.py
segmentpy/_taskManager/__init__.py
segmentpy/_taskManager/augmentationViewer_design.py
segmentpy/_taskManager/augmentationViewer_logic.py
segmentpy/_taskManager/blanketColorPalette_design.py
segmentpy/_taskManager/blanketColorPalette_logic.py
segmentpy/_taskManager/canvas_logic.py
segmentpy/_taskManager/dashboard_design.py
segmentpy/_taskManager/dashboard_logic.py
segmentpy/_taskManager/dialog_design.py
segmentpy/_taskManager/dialog_logic.py
segmentpy/_taskManager/file_dialog.py
segmentpy/_taskManager/gradViewer2_design.py
segmentpy/_taskManager/gradViewer_logic.py
segmentpy/_taskManager/gridSearch_dialog_design.py
segmentpy/_taskManager/gridSearch_dialog_logic.py
segmentpy/_taskManager/mainwindow_design.py
segmentpy/_taskManager/mainwindow_logic.py
segmentpy/_taskManager/metric_design.py
segmentpy/_taskManager/metric_logic.py
segmentpy/_taskManager/nodes_list_design.py
segmentpy/_taskManager/nodes_list_logic.py
segmentpy/_taskManager/opening_design.py
segmentpy/_taskManager/opening_logic.py
segmentpy/_taskManager/pooling_dialog_design.py
segmentpy/_taskManager/pooling_dialog_logic.py
segmentpy/_taskManager/predictDialog_design2.py
segmentpy/_taskManager/predictDialog_logic.py
segmentpy/_taskManager/resultExtractor_design.py
segmentpy/_taskManager/resultExtractor_logic.py
segmentpy/_taskManager/resumeDialog_design.py
segmentpy/_taskManager/resumeDialog_logic.py
segmentpy/_taskManager/sleep.py
segmentpy/_taskManager/trainableParamsList_design.py
segmentpy/_taskManager/trainableParamsList_logic.py
segmentpy/_taskManager/volumes_viewer_design.py
segmentpy/_taskManager/volumes_viewer_logic.py
segmentpy/img/SegmentPy_logo.png
segmentpy/img/exchange.png
segmentpy/img/exchange_2.png
segmentpy/img/floppy-disk.png
segmentpy/img/live.png
segmentpy/img/logo.png
segmentpy/img/minus.png
segmentpy/img/play-button.png
segmentpy/img/plus.png
segmentpy-0.1.dist-info/LICENSE
segmentpy-0.1.dist-info/METADATA
segmentpy-0.1.dist-info/WHEEL
segmentpy-0.1.dist-info/entry_points.txt
segmentpy-0.1.dist-info/top_level.txt
segmentpy-0.1.dist-info/RECORD
